mqroute/__init__.py
mqroute/callback_request.py
mqroute/callback_resolver.py
mqroute/callback_runner.py
mqroute/message_publisher.py
mqroute/mqtt_client.py
mqroute/mqtt_client_userdata.py
mqroute/mqtt_message.py
mqroute/mqtt_subscription.py
mqroute/payload_formats.py
mqroute/publish_message.py
mqroute/qos.py
mqroute/topic_match.py
mqroute/topic_node.py
mqroute-0.4.0.dist-info/LICENSE
mqroute-0.4.0.dist-info/METADATA
mqroute-0.4.0.dist-info/WHEEL
mqroute-0.4.0.dist-info/top_level.txt
mqroute-0.4.0.dist-info/RECORD
